[{
  "id": 0,
  "selected": true,
	"name": "welcome.js",
	"language": "javascript",
	"content": "const personal = {\n  name: \"Lenin Alevski Huerta Arias\",\n  title: [\"Software Engineer\", \"FullStack Engineer\"],\n  email: 'lenin@alevsk.com',\n  education: [\n    {\n      school: \"Tecnologico de Monterrey\",\n      website: \"https://tec.mx/es/\",\n      degree: \"BS in Computer Science\",\n      field: \"Software Engineering\",\n    },\n  ],\n  location: [\"Guadalajara, Mexico\", \"San Francisco, California\"]\n};\n\nconst expertise = [\"Software development\", \"Distributed Systems\", \"System Architecture\", \"Information Security\"];\n\nconst interests = [\"Cybersecurity\", \"Microservices\", \"Cloud\", \"Scalability\"];\n\nconst experience = [\n  {\n    company: \"OneLogin\",\n    website: \"https://www.onelogin.com/\",\n    title: \"Software Engineer\",\n    from: \"January 2019\",\n    to: \"Present\",\n    description: \"Distributed systems Engineer specialized in application security.\",\n  },\n  {\n    company: \"Freeagent CRM\",\n    website: \"https://freeagentcrm.com/\",\n    title: \"Senior Software Engineer\",\n    from: \"November 2016\",\n    to: \"December 2018\",\n    description: \"Platform developer building distributed and highly scalable systems using a very interesting\n      stack of technologies.\",\n  },\n  {\n    company: \"Oracle\",\n    website: \"https://www.oracle.com/\",\n    title: \"Software Engineer\",\n    from: \"March 2016\",\n    to: \"October 2016\",\n    description: \"As a member of the software engineering division I apply my knowledge of software architecture\n      and information security to perform software development tasks associated with debugging, QA testing and\n      security testing.\",\n  },\n  {\n    company: \"Websec Mexico\",\n    website: \"https://www.websec.mx/\",\n    title: \"Software Engineer\",\n    from: \"May 2012\",\n    to: \"March 2016\",\n    description: \"Cybersecurity consultant focused on code reviews, web and network penetration testing.\",\n  },\n];\n  "
}]